mypy_extensions.py
mypy_extensions-0.4.2.dist-info/LICENSE
mypy_extensions-0.4.2.dist-info/METADATA
mypy_extensions-0.4.2.dist-info/WHEEL
mypy_extensions-0.4.2.dist-info/top_level.txt
mypy_extensions-0.4.2.dist-info/RECORD
