Metadata-Version: 2.1
Name: mypy-extensions
Version: 0.4.2
Summary: Experimental type system extensions for programs checked with the mypy typechecker.
Home-page: http://www.mypy-lang.org/
Author: The mypy developers
Author-email: jukka.lehtosalo@iki.fi
License: MIT License
Platform: UNKNOWN
Classifier: Development Status :: 2 - Pre-Alpha
Classifier: Environment :: Console
Classifier: Intended Audience :: Developers
Classifier: License :: OSI Approved :: MIT License
Classifier: Programming Language :: Python :: 2
Classifier: Programming Language :: Python :: 2.7
Classifier: Programming Language :: Python :: 3
Classifier: Programming Language :: Python :: 3.4
Classifier: Programming Language :: Python :: 3.5
Classifier: Programming Language :: Python :: 3.6
Classifier: Programming Language :: Python :: 3.7
Classifier: Topic :: Software Development
Requires-Dist: typing (>=3.5.3) ; python_version < "3.5"
